<?xml version="1.0"?><Report><ReportQuery><Format><ReportTitle>Ventas vs Produccion</ReportTitle><ReportDescription></ReportDescription><PageSize>.DEFAULT</PageSize><PageOrientation>Landscape</PageOrientation><TopMargin></TopMargin><BottomMargin></BottomMargin><RightMargin></RightMargin><LeftMargin></LeftMargin><AutoPaginate>.DEFAULT</AutoPaginate><PdfZoomFactor></PdfZoomFactor><HtmlZoomFactor></HtmlZoomFactor><PageTitleDisplay>.DEFAULT</PageTitleDisplay><PageLayout>.DEFAULT</PageLayout><pdfFont></pdfFont><pdfFontSize></pdfFontSize><PreExecuteCode>NONE</PreExecuteCode><formBetweenRows>solidline</formBetweenRows><gridDisplay>.DEFAULT</gridDisplay><gridSortable>.DEFAULT</gridSortable><gridSearchable>.DEFAULT</gridSearchable><gridPageable>.DEFAULT</gridPageable><gridPageSize>.DEFAULT</gridPageSize></Format><Datasource><SourceType>database</SourceType><SourceConnection><DatabaseType>mysql</DatabaseType><DatabaseName></DatabaseName><HostName></HostName><ServiceName></ServiceName><UserName></UserName><Password></Password></SourceConnection></Datasource><EntryForm><Query><TableSql></TableSql><WhereSql></WhereSql><GroupSql></GroupSql><RowSelection>all</RowSelection><SQL><QuerySql></QuerySql><SQLRaw>SELECT  a.CodArticulo,
    a.Anterior as SaldoInicial,
    a.Descripcion,  
    a.VentasProg as ventasprog,  
    a.ProdProg,
    a.Entrada as ProdReal,
    a.VentasProg as ventasprog,
    a.Salidas as VentasReal,
    a.Anterior+a.ProdProg-a.VentasProg AS Finalprog,
    a.Anterior+a.Entrada-Salidas AS Finalreal
FROM
(SELECT EN01ARTI.CodArticulo, EN01ARTI.Descripcion,
        Sum(IIf(DT02ARTI.Medida = {medida},DT02ARTI.Anterior,0)) AS Anterior,
        Sum(IIf(DT02ARTI.Medida = {medida},DT02ARTI.Entradas,0)) AS Entrada,   
        Sum(IIf(DT02ARTI.Medida = {medida},DT02ARTI.Salidas,0)) AS Salidas,
        0 as VentasProg,
        (CASE WHEN sum(h.Cantidad) is null THEN 0 ELSE sum(h.Cantidad) END) as ProdProg
    FROM DT02ARTI, DT01ARTI, EN01ARTI 
    left join en01prpr h
    on EN01ARTI.CodArticulo= h.CodArticulo
     [and h.Medida={medida}]
     [and h.Periodo={periodo}]
    WHERE (DT02ARTI.CodArticulo = EN01ARTI.CodArticulo)    
    AND (DT01ARTI.CodArticulo = EN01ARTI.CodArticulo)    
    AND (DT01ARTI.CodAlmacen = DT02ARTI.CodAlmacen)     
    [and DT02ARTI.Periodo={periodo}]
    [and (DT01ARTI.CodAlmacen &gt;={almacendesde})] [AND (DT01ARTI.CodAlmacen &lt;={almacenhasta})]
    AND ((Anterior&lt;&gt;0) OR (Entradas&lt;&gt;0) OR (Salidas&lt;&gt;0))
        GROUP BY EN01ARTI.CodArticulo,EN01ARTI.Descripcion) a</SQLRaw></SQL><QueryColumns><QueryColumn><Name>TotalFinalreal</Name><TableName></TableName><ColumnName></ColumnName><ColumnType></ColumnType><ColumnLength></ColumnLength><Format><column_display>hide</column_display><content_type>plain</content_type><ColumnStartPDF></ColumnStartPDF><justify>left</justify><ColumnWidthPDF></ColumnWidthPDF><ColumnWidthHTML></ColumnWidthHTML><column_title></column_title><tooltip></tooltip><group_header_label> </group_header_label><group_header_label_xpos></group_header_label_xpos><group_header_data_xpos></group_header_data_xpos><group_trailer_label> </group_trailer_label></Format></QueryColumn><QueryColumn><Name>SaldoInicial</Name><TableName></TableName><ColumnName>a.Anterior as</ColumnName><ColumnType>char</ColumnType><ColumnLength>30</ColumnLength><Format><column_display>show</column_display><content_type>plain</content_type><ColumnStartPDF></ColumnStartPDF><justify>right</justify><ColumnWidthPDF></ColumnWidthPDF><ColumnWidthHTML>10%</ColumnWidthHTML><column_title>Saldo Inicial</column_title><tooltip></tooltip><group_header_label>0</group_header_label><group_header_label_xpos></group_header_label_xpos><group_header_data_xpos></group_header_data_xpos><group_trailer_label>0</group_trailer_label></Format></QueryColumn><QueryColumn><Name>TotalSaldoInicial</Name><TableName></TableName><ColumnName></ColumnName><ColumnType></ColumnType><ColumnLength></ColumnLength><Format><column_display>hide</column_display><content_type>plain</content_type><ColumnStartPDF></ColumnStartPDF><justify>left</justify><ColumnWidthPDF></ColumnWidthPDF><ColumnWidthHTML></ColumnWidthHTML><column_title></column_title><tooltip></tooltip><group_header_label> </group_header_label><group_header_label_xpos></group_header_label_xpos><group_header_data_xpos></group_header_data_xpos><group_trailer_label> </group_trailer_label></Format></QueryColumn><QueryColumn><Name>TotalProdProg</Name><TableName></TableName><ColumnName></ColumnName><ColumnType></ColumnType><ColumnLength></ColumnLength><Format><column_display>hide</column_display><content_type>plain</content_type><ColumnStartPDF></ColumnStartPDF><justify>left</justify><ColumnWidthPDF></ColumnWidthPDF><ColumnWidthHTML></ColumnWidthHTML><column_title></column_title><tooltip></tooltip><group_header_label> </group_header_label><group_header_label_xpos></group_header_label_xpos><group_header_data_xpos></group_header_data_xpos><group_trailer_label> </group_trailer_label></Format></QueryColumn><QueryColumn><Name>ProdReal</Name><TableName></TableName><ColumnName>a.Entrada as</ColumnName><ColumnType>char</ColumnType><ColumnLength>30</ColumnLength><Format><column_display>show</column_display><content_type>plain</content_type><ColumnStartPDF></ColumnStartPDF><justify>right</justify><ColumnWidthPDF></ColumnWidthPDF><ColumnWidthHTML>10%</ColumnWidthHTML><column_title>Prod Real</column_title><tooltip></tooltip><group_header_label>0</group_header_label><group_header_label_xpos></group_header_label_xpos><group_header_data_xpos></group_header_data_xpos><group_trailer_label>0</group_trailer_label></Format></QueryColumn><QueryColumn><Name>ventasprog</Name><TableName></TableName><ColumnName>a.VentasProg as</ColumnName><ColumnType>char</ColumnType><ColumnLength>30</ColumnLength><Format><column_display>show</column_display><content_type>plain</content_type><ColumnStartPDF></ColumnStartPDF><justify>right</justify><ColumnWidthPDF></ColumnWidthPDF><ColumnWidthHTML>10%</ColumnWidthHTML><column_title>Ventas Prog</column_title><tooltip></tooltip><group_header_label>0</group_header_label><group_header_label_xpos></group_header_label_xpos><group_header_data_xpos></group_header_data_xpos><group_trailer_label>0</group_trailer_label></Format></QueryColumn><QueryColumn><Name>VentasReal</Name><TableName></TableName><ColumnName>a.Salidas as</ColumnName><ColumnType>char</ColumnType><ColumnLength>30</ColumnLength><Format><column_display>show</column_display><content_type>plain</content_type><ColumnStartPDF></ColumnStartPDF><justify>right</justify><ColumnWidthPDF></ColumnWidthPDF><ColumnWidthHTML>10%</ColumnWidthHTML><column_title>Ventas Real</column_title><tooltip></tooltip><group_header_label>0</group_header_label><group_header_label_xpos></group_header_label_xpos><group_header_data_xpos></group_header_data_xpos><group_trailer_label>0</group_trailer_label></Format></QueryColumn><QueryColumn><Name>TotalProdReal</Name><TableName></TableName><ColumnName></ColumnName><ColumnType></ColumnType><ColumnLength></ColumnLength><Format><column_display>hide</column_display><content_type>plain</content_type><ColumnStartPDF></ColumnStartPDF><justify>left</justify><ColumnWidthPDF></ColumnWidthPDF><ColumnWidthHTML></ColumnWidthHTML><column_title></column_title><tooltip></tooltip><group_header_label> </group_header_label><group_header_label_xpos></group_header_label_xpos><group_header_data_xpos></group_header_data_xpos><group_trailer_label> </group_trailer_label></Format></QueryColumn><QueryColumn><Name>Finalprog</Name><TableName></TableName><ColumnName>a.Anterior+a.ProdProg-a.VentasProg AS</ColumnName><ColumnType>char</ColumnType><ColumnLength>30</ColumnLength><Format><column_display>show</column_display><content_type>plain</content_type><ColumnStartPDF></ColumnStartPDF><justify>right</justify><ColumnWidthPDF></ColumnWidthPDF><ColumnWidthHTML>10%</ColumnWidthHTML><column_title>Final Prog</column_title><tooltip></tooltip><group_header_label>0</group_header_label><group_header_label_xpos></group_header_label_xpos><group_header_data_xpos></group_header_data_xpos><group_trailer_label>0</group_trailer_label></Format></QueryColumn><QueryColumn><Name>Finalreal</Name><TableName></TableName><ColumnName>a.Anterior+a.Entrada-Salidas AS</ColumnName><ColumnType>char</ColumnType><ColumnLength>30</ColumnLength><Format><column_display>show</column_display><content_type>plain</content_type><ColumnStartPDF></ColumnStartPDF><justify>right</justify><ColumnWidthPDF></ColumnWidthPDF><ColumnWidthHTML>10%</ColumnWidthHTML><column_title>Final Real</column_title><tooltip></tooltip><group_header_label>0</group_header_label><group_header_label_xpos></group_header_label_xpos><group_header_data_xpos></group_header_data_xpos><group_trailer_label>0</group_trailer_label></Format></QueryColumn><QueryColumn><Name>Totalventasprog</Name><TableName></TableName><ColumnName></ColumnName><ColumnType></ColumnType><ColumnLength></ColumnLength><Format><column_display>hide</column_display><content_type>plain</content_type><ColumnStartPDF></ColumnStartPDF><justify>left</justify><ColumnWidthPDF></ColumnWidthPDF><ColumnWidthHTML></ColumnWidthHTML><column_title></column_title><tooltip></tooltip><group_header_label> </group_header_label><group_header_label_xpos></group_header_label_xpos><group_header_data_xpos></group_header_data_xpos><group_trailer_label> </group_trailer_label></Format></QueryColumn><QueryColumn><Name>TotalVentasReal</Name><TableName></TableName><ColumnName></ColumnName><ColumnType></ColumnType><ColumnLength></ColumnLength><Format><column_display>hide</column_display><content_type>plain</content_type><ColumnStartPDF></ColumnStartPDF><justify>left</justify><ColumnWidthPDF></ColumnWidthPDF><ColumnWidthHTML></ColumnWidthHTML><column_title></column_title><tooltip></tooltip><group_header_label> </group_header_label><group_header_label_xpos></group_header_label_xpos><group_header_data_xpos></group_header_data_xpos><group_trailer_label> </group_trailer_label></Format></QueryColumn><QueryColumn><Name>TotalFinalprog</Name><TableName></TableName><ColumnName></ColumnName><ColumnType></ColumnType><ColumnLength></ColumnLength><Format><column_display>hide</column_display><content_type>plain</content_type><ColumnStartPDF></ColumnStartPDF><justify>left</justify><ColumnWidthPDF></ColumnWidthPDF><ColumnWidthHTML></ColumnWidthHTML><column_title></column_title><tooltip></tooltip><group_header_label> </group_header_label><group_header_label_xpos></group_header_label_xpos><group_header_data_xpos></group_header_data_xpos><group_trailer_label> </group_trailer_label></Format></QueryColumn><QueryColumn><Name>etiquetaTotal</Name><TableName></TableName><ColumnName></ColumnName><ColumnType></ColumnType><ColumnLength></ColumnLength><Format><column_display>hide</column_display><content_type>plain</content_type><ColumnStartPDF></ColumnStartPDF><justify>left</justify><ColumnWidthPDF></ColumnWidthPDF><ColumnWidthHTML></ColumnWidthHTML><column_title></column_title><tooltip></tooltip><group_header_label> </group_header_label><group_header_label_xpos></group_header_label_xpos><group_header_data_xpos></group_header_data_xpos><group_trailer_label> </group_trailer_label></Format></QueryColumn><QueryColumn><Name>porcentaje</Name><TableName></TableName><ColumnName></ColumnName><ColumnType></ColumnType><ColumnLength></ColumnLength><Format><column_display>show</column_display><content_type>plain</content_type><ColumnStartPDF></ColumnStartPDF><justify>right</justify><ColumnWidthPDF></ColumnWidthPDF><ColumnWidthHTML>4%</ColumnWidthHTML><column_title>%</column_title><tooltip></tooltip><group_header_label> </group_header_label><group_header_label_xpos></group_header_label_xpos><group_header_data_xpos></group_header_data_xpos><group_trailer_label> </group_trailer_label></Format></QueryColumn><QueryColumn><Name>TotalPorcentaje</Name><TableName></TableName><ColumnName></ColumnName><ColumnType></ColumnType><ColumnLength></ColumnLength><Format><column_display>hide</column_display><content_type>plain</content_type><ColumnStartPDF></ColumnStartPDF><justify>left</justify><ColumnWidthPDF></ColumnWidthPDF><ColumnWidthHTML></ColumnWidthHTML><column_title></column_title><tooltip></tooltip><group_header_label> </group_header_label><group_header_label_xpos></group_header_label_xpos><group_header_data_xpos></group_header_data_xpos><group_trailer_label> </group_trailer_label></Format></QueryColumn><QueryColumn><Name>Descripcion</Name><TableName>a</TableName><ColumnName>Descripcion</ColumnName><ColumnType>char</ColumnType><ColumnLength>30</ColumnLength><Format><column_display>show</column_display><content_type>plain</content_type><ColumnStartPDF></ColumnStartPDF><justify>left</justify><ColumnWidthPDF></ColumnWidthPDF><ColumnWidthHTML></ColumnWidthHTML><column_title></column_title><tooltip></tooltip><group_header_label>0</group_header_label><group_header_label_xpos></group_header_label_xpos><group_header_data_xpos></group_header_data_xpos><group_trailer_label>0</group_trailer_label></Format></QueryColumn><QueryColumn><Name>CodArticulo</Name><TableName>a</TableName><ColumnName>CodArticulo</ColumnName><ColumnType>char</ColumnType><ColumnLength>30</ColumnLength><Format><column_display>show</column_display><content_type>plain</content_type><ColumnStartPDF></ColumnStartPDF><justify>left</justify><ColumnWidthPDF></ColumnWidthPDF><ColumnWidthHTML>9%</ColumnWidthHTML><column_title></column_title><tooltip></tooltip><group_header_label>0</group_header_label><group_header_label_xpos></group_header_label_xpos><group_header_data_xpos></group_header_data_xpos><group_trailer_label>0</group_trailer_label></Format></QueryColumn><QueryColumn><Name>ProdProg</Name><TableName>a</TableName><ColumnName>ProdProg</ColumnName><ColumnType>char</ColumnType><ColumnLength>30</ColumnLength><Format><column_display>show</column_display><content_type>plain</content_type><ColumnStartPDF></ColumnStartPDF><justify>right</justify><ColumnWidthPDF></ColumnWidthPDF><ColumnWidthHTML>10%</ColumnWidthHTML><column_title>Prod Prog</column_title><tooltip></tooltip><group_header_label>0</group_header_label><group_header_label_xpos></group_header_label_xpos><group_header_data_xpos></group_header_data_xpos><group_trailer_label>0</group_trailer_label></Format></QueryColumn></QueryColumns><OrderColumns></OrderColumns><PreSQLS></PreSQLS></Query><Assignments><Assignment><AssignName>TotalFinalreal</AssignName><AssignNameNew></AssignNameNew><Expression>number_format(sum({Finalreal}),2,',','.')</Expression><Condition></Condition></Assignment><Assignment><AssignName>TotalSaldoInicial</AssignName><AssignNameNew></AssignNameNew><Expression>number_format(sum({SaldoInicial}),2,',','.')</Expression><Condition></Condition></Assignment><Assignment><AssignName>TotalProdProg</AssignName><AssignNameNew></AssignNameNew><Expression>number_format(sum({ProdProg}),2,',','.')</Expression><Condition></Condition></Assignment><Assignment><AssignName>TotalProdReal</AssignName><AssignNameNew></AssignNameNew><Expression>number_format(sum({ProdReal}),2,',','.')</Expression><Condition></Condition></Assignment><Assignment><AssignName>Totalventasprog</AssignName><AssignNameNew></AssignNameNew><Expression>number_format(sum({ventasprog}),2,',','.')</Expression><Condition></Condition></Assignment><Assignment><AssignName>TotalVentasReal</AssignName><AssignNameNew></AssignNameNew><Expression>number_format(sum({VentasReal}),2,',','.')</Expression><Condition></Condition></Assignment><Assignment><AssignName>TotalFinalprog</AssignName><AssignNameNew></AssignNameNew><Expression>number_format(sum({Finalprog}),2,',','.')</Expression><Condition></Condition></Assignment><Assignment><AssignName>TotalPorcentaje</AssignName><AssignNameNew></AssignNameNew><Expression>(sum({Finalprog}) != 0) ? number_format((((sum({Finalreal}) * 100) / sum({Finalprog}) ) - 100),2,',','.') : number_format(0, 2,',','.')</Expression><Condition></Condition></Assignment><Assignment><AssignName>Finalreal</AssignName><AssignNameNew></AssignNameNew><Expression>number_format({Finalreal},2,',','.')</Expression><Condition></Condition></Assignment><Assignment><AssignName>SaldoInicial</AssignName><AssignNameNew></AssignNameNew><Expression>number_format({SaldoInicial},2,',','.')</Expression><Condition></Condition></Assignment><Assignment><AssignName>ProdReal</AssignName><AssignNameNew></AssignNameNew><Expression>number_format({ProdReal},2,',','.')</Expression><Condition></Condition></Assignment><Assignment><AssignName>VentasReal</AssignName><AssignNameNew></AssignNameNew><Expression>number_format({VentasReal},2,',','.')</Expression><Condition></Condition></Assignment><Assignment><AssignName>etiquetaTotal</AssignName><AssignNameNew></AssignNameNew><Expression>'TOTAL'</Expression><Condition></Condition></Assignment><Assignment><AssignName>porcentaje</AssignName><AssignNameNew></AssignNameNew><Expression>number_format(0, 2,',','.')</Expression><Condition></Condition></Assignment><Assignment><AssignName>ProdProg</AssignName><AssignNameNew></AssignNameNew><Expression>number_format({ProdProg},2,',','.')</Expression><Condition></Condition></Assignment><Assignment><AssignName>ventasprog</AssignName><AssignNameNew></AssignNameNew><Expression>number_format({ventasprog},2,',','.')</Expression><Condition></Condition></Assignment><Assignment><AssignName>Finalprog</AssignName><AssignNameNew></AssignNameNew><Expression>number_format({Finalprog},2,',','.')</Expression><Condition></Condition></Assignment></Assignments><Criteria><CriteriaItem><Name>periodo</Name><Title>Periodo</Title><QueryTableName></QueryTableName><QueryColumnName></QueryColumnName><CriteriaType>LIST</CriteriaType><CriteriaHelp></CriteriaHelp><CriteriaDisplay>DROPDOWN</CriteriaDisplay><ExpandDisplay>NOINPUT</ExpandDisplay><CriteriaRequired>.DEFAULT</CriteriaRequired><CriteriaHidden>.DEFAULT</CriteriaHidden><CriteriaDisplayGroup></CriteriaDisplayGroup><ReturnColumn></ReturnColumn><DisplayColumn></DisplayColumn><OverviewColumn></OverviewColumn><MatchColumn></MatchColumn><CriteriaDefaults></CriteriaDefaults><CriteriaList>00=00, 01=01, 02=02, 03=03, 04=04,05=05, 06=06,07=07, 08=08,09=09,10=10, 11=11</CriteriaList><Query><TableSql></TableSql><WhereSql></WhereSql><GroupSql></GroupSql><RowSelection></RowSelection><SQLRaw></SQLRaw><SQL><QuerySql></QuerySql></SQL><QueryColumns></QueryColumns><OrderColumns></OrderColumns><Assignments></Assignments></Query><CriteriaLinks></CriteriaLinks></CriteriaItem><CriteriaItem><Name>almacendesde</Name><Title>Almacen Desde</Title><QueryTableName></QueryTableName><QueryColumnName></QueryColumnName><CriteriaType>LOOKUP</CriteriaType><CriteriaHelp></CriteriaHelp><CriteriaDisplay>DROPDOWN</CriteriaDisplay><ExpandDisplay>NOINPUT</ExpandDisplay><CriteriaRequired>.DEFAULT</CriteriaRequired><CriteriaHidden>.DEFAULT</CriteriaHidden><CriteriaDisplayGroup></CriteriaDisplayGroup><ReturnColumn>CodAlmacen</ReturnColumn><DisplayColumn>descripcion2</DisplayColumn><OverviewColumn>CodAlmacen</OverviewColumn><MatchColumn>CodAlmacen</MatchColumn><CriteriaDefaults></CriteriaDefaults><CriteriaList></CriteriaList><Query><TableSql></TableSql><WhereSql></WhereSql><GroupSql></GroupSql><RowSelection></RowSelection><SQLRaw>SELECT CodAlmacen,concat(CodAlmacen,' / ',DesAlmacen) as descripcion2
FROM  mt01alma
order by CodAlmacen</SQLRaw><SQL><QuerySql></QuerySql></SQL><QueryColumns><QueryColumn><Name>CodAlmacen</Name><TableName></TableName><ColumnName>CodAlmacen</ColumnName><ColumnType>char</ColumnType><ColumnLength>30</ColumnLength><Format><column_display>show</column_display><content_type>plain</content_type><justify>left</justify></Format></QueryColumn><QueryColumn><Name>descripcion2</Name><TableName></TableName><ColumnName>concat(CodAlmacen,' / ',DesAlmacen) as</ColumnName><ColumnType>char</ColumnType><ColumnLength>30</ColumnLength><Format><column_display>show</column_display><content_type>plain</content_type><justify>left</justify></Format></QueryColumn></QueryColumns><OrderColumns></OrderColumns><Assignments></Assignments></Query><CriteriaLinks></CriteriaLinks></CriteriaItem><CriteriaItem><Name>almacenhasta</Name><Title>Almacen Hasta</Title><QueryTableName></QueryTableName><QueryColumnName></QueryColumnName><CriteriaType>LOOKUP</CriteriaType><CriteriaHelp></CriteriaHelp><CriteriaDisplay>DROPDOWN</CriteriaDisplay><ExpandDisplay>NOINPUT</ExpandDisplay><CriteriaRequired>.DEFAULT</CriteriaRequired><CriteriaHidden>.DEFAULT</CriteriaHidden><CriteriaDisplayGroup></CriteriaDisplayGroup><ReturnColumn>CodAlmacen</ReturnColumn><DisplayColumn>descripcion2</DisplayColumn><OverviewColumn>CodAlmacen</OverviewColumn><MatchColumn>CodAlmacen</MatchColumn><CriteriaDefaults></CriteriaDefaults><CriteriaList></CriteriaList><Query><TableSql></TableSql><WhereSql></WhereSql><GroupSql></GroupSql><RowSelection></RowSelection><SQLRaw>SELECT CodAlmacen,concat(CodAlmacen,' / ',DesAlmacen) as descripcion2
FROM  mt01alma
order by CodAlmacen</SQLRaw><SQL><QuerySql></QuerySql></SQL><QueryColumns><QueryColumn><Name>CodAlmacen</Name><TableName></TableName><ColumnName>CodAlmacen</ColumnName><ColumnType>char</ColumnType><ColumnLength>30</ColumnLength><Format><column_display>show</column_display><content_type>plain</content_type><justify>left</justify></Format></QueryColumn><QueryColumn><Name>descripcion2</Name><TableName></TableName><ColumnName>concat(CodAlmacen,' / ',DesAlmacen) as</ColumnName><ColumnType>char</ColumnType><ColumnLength>30</ColumnLength><Format><column_display>show</column_display><content_type>plain</content_type><justify>left</justify></Format></QueryColumn></QueryColumns><OrderColumns></OrderColumns><Assignments></Assignments></Query><CriteriaLinks></CriteriaLinks></CriteriaItem><CriteriaItem><Name>medida</Name><Title>Medida</Title><QueryTableName></QueryTableName><QueryColumnName></QueryColumnName><CriteriaType>LIST</CriteriaType><CriteriaHelp></CriteriaHelp><CriteriaDisplay>DROPDOWN</CriteriaDisplay><ExpandDisplay>NOINPUT</ExpandDisplay><CriteriaRequired>.DEFAULT</CriteriaRequired><CriteriaHidden>.DEFAULT</CriteriaHidden><CriteriaDisplayGroup></CriteriaDisplayGroup><ReturnColumn></ReturnColumn><DisplayColumn></DisplayColumn><OverviewColumn></OverviewColumn><MatchColumn></MatchColumn><CriteriaDefaults></CriteriaDefaults><CriteriaList> MTS2=MTS2, KG=KG</CriteriaList><Query><TableSql></TableSql><WhereSql></WhereSql><GroupSql></GroupSql><RowSelection></RowSelection><SQLRaw></SQLRaw><SQL><QuerySql></QuerySql></SQL><QueryColumns></QueryColumns><OrderColumns></OrderColumns><Assignments></Assignments></Query><CriteriaLinks></CriteriaLinks></CriteriaItem></Criteria><Output><PageHeaders></PageHeaders><PageFooters></PageFooters><DisplayOrders><DisplayOrder><ColumnName>CodArticulo</ColumnName><OrderNumber>1</OrderNumber></DisplayOrder><DisplayOrder><ColumnName>Descripcion</ColumnName><OrderNumber>2</OrderNumber></DisplayOrder><DisplayOrder><ColumnName>SaldoInicial</ColumnName><OrderNumber>3</OrderNumber></DisplayOrder><DisplayOrder><ColumnName>ProdProg</ColumnName><OrderNumber>4</OrderNumber></DisplayOrder><DisplayOrder><ColumnName>ProdReal</ColumnName><OrderNumber>5</OrderNumber></DisplayOrder><DisplayOrder><ColumnName>ventasprog</ColumnName><OrderNumber>6</OrderNumber></DisplayOrder><DisplayOrder><ColumnName>VentasReal</ColumnName><OrderNumber>7</OrderNumber></DisplayOrder><DisplayOrder><ColumnName>TotalFinalreal</ColumnName><OrderNumber>8</OrderNumber></DisplayOrder><DisplayOrder><ColumnName>TotalSaldoInicial</ColumnName><OrderNumber>9</OrderNumber></DisplayOrder><DisplayOrder><ColumnName>TotalProdProg</ColumnName><OrderNumber>10</OrderNumber></DisplayOrder><DisplayOrder><ColumnName>TotalProdReal</ColumnName><OrderNumber>11</OrderNumber></DisplayOrder><DisplayOrder><ColumnName>Totalventasprog</ColumnName><OrderNumber>12</OrderNumber></DisplayOrder><DisplayOrder><ColumnName>TotalVentasReal</ColumnName><OrderNumber>13</OrderNumber></DisplayOrder><DisplayOrder><ColumnName>TotalFinalprog</ColumnName><OrderNumber>14</OrderNumber></DisplayOrder><DisplayOrder><ColumnName>etiquetaTotal</ColumnName><OrderNumber>15</OrderNumber></DisplayOrder><DisplayOrder><ColumnName>TotalPorcentaje</ColumnName><OrderNumber>16</OrderNumber></DisplayOrder><DisplayOrder><ColumnName>Finalprog</ColumnName><OrderNumber>17</OrderNumber></DisplayOrder><DisplayOrder><ColumnName>Finalreal</ColumnName><OrderNumber>18</OrderNumber></DisplayOrder><DisplayOrder><ColumnName>porcentaje</ColumnName><OrderNumber>19</OrderNumber></DisplayOrder></DisplayOrders><Groups><Group><GroupName>REPORT_BODY</GroupName><BeforeGroupHeader>blankline</BeforeGroupHeader><AfterGroupHeader>blankline</AfterGroupHeader><BeforeGroupTrailer>blankline</BeforeGroupTrailer><AfterGroupTrailer>blankline</AfterGroupTrailer><GroupHeaders></GroupHeaders><GroupTrailers><GroupTrailer><GroupTrailerDisplayColumn>Finalreal</GroupTrailerDisplayColumn><GroupTrailerValueColumn>TotalFinalreal</GroupTrailerValueColumn><GroupTrailerCustom></GroupTrailerCustom><ShowInHTML>yes</ShowInHTML><ShowInPDF>yes</ShowInPDF></GroupTrailer><GroupTrailer><GroupTrailerDisplayColumn>SaldoInicial</GroupTrailerDisplayColumn><GroupTrailerValueColumn>TotalSaldoInicial</GroupTrailerValueColumn><GroupTrailerCustom></GroupTrailerCustom><ShowInHTML>yes</ShowInHTML><ShowInPDF>yes</ShowInPDF></GroupTrailer><GroupTrailer><GroupTrailerDisplayColumn>ProdReal</GroupTrailerDisplayColumn><GroupTrailerValueColumn>TotalProdReal</GroupTrailerValueColumn><GroupTrailerCustom></GroupTrailerCustom><ShowInHTML>yes</ShowInHTML><ShowInPDF>yes</ShowInPDF></GroupTrailer><GroupTrailer><GroupTrailerDisplayColumn>VentasReal</GroupTrailerDisplayColumn><GroupTrailerValueColumn>TotalVentasReal</GroupTrailerValueColumn><GroupTrailerCustom></GroupTrailerCustom><ShowInHTML>yes</ShowInHTML><ShowInPDF>yes</ShowInPDF></GroupTrailer><GroupTrailer><GroupTrailerDisplayColumn>porcentaje</GroupTrailerDisplayColumn><GroupTrailerValueColumn>TotalPorcentaje</GroupTrailerValueColumn><GroupTrailerCustom></GroupTrailerCustom><ShowInHTML>yes</ShowInHTML><ShowInPDF>yes</ShowInPDF></GroupTrailer><GroupTrailer><GroupTrailerDisplayColumn>ProdProg</GroupTrailerDisplayColumn><GroupTrailerValueColumn>TotalProdProg</GroupTrailerValueColumn><GroupTrailerCustom></GroupTrailerCustom><ShowInHTML>yes</ShowInHTML><ShowInPDF>yes</ShowInPDF></GroupTrailer><GroupTrailer><GroupTrailerDisplayColumn>ventasprog</GroupTrailerDisplayColumn><GroupTrailerValueColumn>Totalventasprog</GroupTrailerValueColumn><GroupTrailerCustom></GroupTrailerCustom><ShowInHTML>yes</ShowInHTML><ShowInPDF>yes</ShowInPDF></GroupTrailer><GroupTrailer><GroupTrailerDisplayColumn>Finalprog</GroupTrailerDisplayColumn><GroupTrailerValueColumn>TotalFinalprog</GroupTrailerValueColumn><GroupTrailerCustom></GroupTrailerCustom><ShowInHTML>yes</ShowInHTML><ShowInPDF>yes</ShowInPDF></GroupTrailer></GroupTrailers></Group></Groups><Graphs></Graphs></Output></EntryForm></ReportQuery></Report>